napari_nuclephaser/__init__.py
napari_nuclephaser/_version.py
napari_nuclephaser/calibrate_dapi.py
napari_nuclephaser/calibrate_known_number.py
napari_nuclephaser/calibrate_points.py
napari_nuclephaser/convert_points_to_labels.py
napari_nuclephaser/count_points.py
napari_nuclephaser/napari.yaml
napari_nuclephaser/predict_on_single.py
napari_nuclephaser/predict_one_stack.py
napari_nuclephaser/predict_two_stack.py
napari_nuclephaser/utils.py
napari_nuclephaser/_tests/__init__.py
napari_nuclephaser/_tests/test_widget_calibrate_with_dapi.py
napari_nuclephaser/_tests/test_widget_calibrate_with_known_number.py
napari_nuclephaser/_tests/test_widget_calibrate_with_points.py
napari_nuclephaser/_tests/test_widget_make_points.py
napari_nuclephaser/_tests/test_widget_predict_on_stack.py
napari_nuclephaser/models/ND_v11n.pt
napari_nuclephaser/models/ND_v11s.pt
napari_nuclephaser/models/ND_v5n.pt
napari_nuclephaser/models/ND_v5s.pt
napari_nuclephaser/models/Fluorescent nuclei detectors/dapi_v5.pt
napari_nuclephaser-0.2.4.dist-info/licenses/LICENSE
napari_nuclephaser-0.2.4.dist-info/METADATA
napari_nuclephaser-0.2.4.dist-info/WHEEL
napari_nuclephaser-0.2.4.dist-info/entry_points.txt
napari_nuclephaser-0.2.4.dist-info/top_level.txt
napari_nuclephaser-0.2.4.dist-info/RECORD
