Metadata-Version: 2.4
Name: napari-nuclephaser
Version: 0.2.4
Summary: A Napari plugin to detect and count nuclei on phase contrast images
Author: Nikita Voloshin
Author-email: nikita.voloshin.98@gmail.com
License: MIT License
Project-URL: Bug Tracker, https://github.com/nikvo1/napari-nuclephaser/issues
Project-URL: Documentation, https://github.com/nikvo1/napari-nuclephaser#README.md
Project-URL: Source Code, https://github.com/nikvo1/napari-nuclephaser
Project-URL: User Support, https://github.com/nikvo1/napari-nuclephaser/issues
Classifier: Development Status :: 2 - Pre-Alpha
Classifier: Framework :: napari
Classifier: Intended Audience :: Developers
Classifier: License :: OSI Approved :: MIT License
Classifier: Operating System :: OS Independent
Classifier: Programming Language :: Python
Classifier: Programming Language :: Python :: 3
Classifier: Programming Language :: Python :: 3 :: Only
Classifier: Programming Language :: Python :: 3.10
Classifier: Programming Language :: Python :: 3.11
Classifier: Programming Language :: Python :: 3.12
Classifier: Programming Language :: Python :: 3.13
Classifier: Topic :: Scientific/Engineering :: Image Processing
Requires-Python: >=3.10
License-File: LICENSE
Requires-Dist: setuptools
Requires-Dist: wheel
Requires-Dist: napari
Requires-Dist: ultralytics==8.3.141
Requires-Dist: yolov5
Requires-Dist: magicgui
Requires-Dist: sahi
Requires-Dist: scikit-image
Requires-Dist: torch==2.8.0
Requires-Dist: pathlib
Requires-Dist: numpy
Requires-Dist: typing
Requires-Dist: pandas
Requires-Dist: openpyxl
Requires-Dist: seaborn
Requires-Dist: opencv-python
Requires-Dist: imagecodecs
Provides-Extra: testing
Requires-Dist: tox; extra == "testing"
Requires-Dist: pytest; extra == "testing"
Requires-Dist: pytest-cov; extra == "testing"
Requires-Dist: pytest-qt; extra == "testing"
Requires-Dist: pytest-mock; extra == "testing"
Requires-Dist: napari; extra == "testing"
Requires-Dist: pyqt5; extra == "testing"
Requires-Dist: opencv-python-headless; extra == "testing"
Dynamic: license-file
